phabfive/__init__.py
phabfive/cli.py
phabfive/constants.py
phabfive/core.py
phabfive/diffusion.py
phabfive/exceptions.py
phabfive/maniphest.py
phabfive/maniphest_transitions.py
phabfive/passphrase.py
phabfive/paste.py
phabfive/priority_transitions.py
phabfive/project_filters.py
phabfive/repl.py
phabfive/status_transitions.py
phabfive/user.py
phabfive-0.5.0.dist-info/METADATA
phabfive-0.5.0.dist-info/WHEEL
phabfive-0.5.0.dist-info/entry_points.txt
phabfive-0.5.0.dist-info/licenses/LICENSE
phabfive-0.5.0.dist-info/RECORD
