Metadata-Version: 2.4
Name: phabfive
Version: 0.5.0
Summary: A command line tool to interact with Phabricator
Project-URL: Homepage, https://github.com/dynamist/phabfive
Project-URL: Download, https://github.com/dynamist/phabfive/releases
Author-email: Rickard Eriksson <rickard@dynamist.se>
License: Apache License 2.0
License-File: LICENSE
Classifier: Development Status :: 4 - Beta
Classifier: Environment :: Console
Classifier: Intended Audience :: Developers
Classifier: Intended Audience :: System Administrators
Classifier: License :: OSI Approved :: Apache Software License
Classifier: Natural Language :: English
Classifier: Operating System :: OS Independent
Classifier: Programming Language :: Python
Classifier: Programming Language :: Python :: 3.10
Classifier: Programming Language :: Python :: 3.11
Classifier: Programming Language :: Python :: 3.12
Classifier: Programming Language :: Python :: 3.13
Classifier: Programming Language :: Python :: 3.14
Requires-Python: >=3.10
Requires-Dist: anyconfig>=0.10.0
Requires-Dist: appdirs
Requires-Dist: docopt-ng
Requires-Dist: jinja2
Requires-Dist: mkdocs>=1.6.1
Requires-Dist: phabricator
Requires-Dist: pyyaml
Requires-Dist: rich>=13.0.0
Requires-Dist: ruamel-yaml>=0.18.16
Provides-Extra: docs
Requires-Dist: mkdocs; extra == 'docs'
